dotdict3.py
dotdict3-1.4.1.dist-info/licenses/LICENSE
dotdict3-1.4.1.dist-info/METADATA
dotdict3-1.4.1.dist-info/WHEEL
dotdict3-1.4.1.dist-info/top_level.txt
dotdict3-1.4.1.dist-info/RECORD
