Metadata-Version: 2.4
Name: dotdict3
Version: 1.4.1
Summary: Add dot notation to Python dicts.
Author-email: Patrick Elmer <patrick@elmer.ws>
License: MIT License
Project-URL: Home, https://github.com/dotdict/dotdict3
Classifier: License :: OSI Approved :: MIT License
License-File: LICENSE
Provides-Extra: dev
Requires-Dist: pytest; extra == "dev"
Dynamic: license-file
